ganymede_aux-0.5.2.dist-info/WHEEL
ganymede_aux-0.5.2.dist-info/METADATA
ganymede_aux-0.5.2.dist-info/RECORD
ganymede_aux-0.5.2.dist-info/LICENSE
ganymede_aux-0.5.2.dist-info/top_level.txt
ganymede/random.py
ganymede/file.py
ganymede/argument.py
ganymede/json.py
ganymede/filesystem.py
ganymede/__init__.py
ganymede/dataset/i_dataset_loader.py
ganymede/dataset/dataset_aggregator.py
ganymede/dataset/batch_sampler.py
ganymede/dataset/__init__.py
ganymede/dataset/processing/heatmap.py
ganymede/dataset/processing/heatmap_keypoint_batch_processor.py
ganymede/dataset/processing/auxiliary.py
ganymede/dataset/processing/__init__.py
ganymede/dataset/processing/block_keypoint_batch_processor.py
ganymede/dataset/data/bbox_object_markup.py
ganymede/dataset/data/segment_object_markup.py
ganymede/dataset/data/evaluate_type.py
ganymede/dataset/data/__init__.py
ganymede/dataset/coco/coco_dataset_loader.py
ganymede/dataset/coco/__init__.py
ganymede/dataset/export/darknet_format.py
ganymede/dataset/export/__init__.py
ganymede/dataset/cvat/__init__.py
ganymede/dataset/cvat/v1d1_parsing.py
ganymede/dataset/cvat/cvat_image_markup.py
ganymede/dataset/cvat/shapes/cvat_points_shape.py
ganymede/dataset/cvat/shapes/cvat_polygon_shape.py
ganymede/dataset/cvat/shapes/auxiliary.py
ganymede/dataset/cvat/shapes/cvat_polyline_shape.py
ganymede/dataset/cvat/shapes/cvat_box_shape.py
ganymede/dataset/cvat/shapes/__init__.py
ganymede/ml/__init__.py
ganymede/ml/onnxruntime/validation.py
ganymede/ml/onnxruntime/exception.py
ganymede/ml/onnxruntime/__init__.py
ganymede/ml/onnxruntime/detectors/yolo_onnxruntime_detector.py
ganymede/ml/onnxruntime/detectors/auxiliary.py
ganymede/ml/onnxruntime/detectors/__init__.py
ganymede/ml/configuration/environment_parameters.py
ganymede/ml/configuration/train_state.py
ganymede/ml/configuration/train_parameters.py
ganymede/ml/configuration/__init__.py
ganymede/ml/data/object_detection.py
ganymede/ml/data/__init__.py
ganymede/ml/pytorch/__init__.py
ganymede/ml/pytorch/tensor.py
ganymede/ml/pytorch/preprocessing/class_segmentation_processor.py
ganymede/ml/pytorch/preprocessing/binary_segmentation_processor.py
